criteo_fork_opencensus-1.0.9.dist-info/METADATA
criteo_fork_opencensus-1.0.9.dist-info/RECORD
criteo_fork_opencensus-1.0.9.dist-info/WHEEL
criteo_fork_opencensus-1.0.9.dist-info/namespace_packages.txt
criteo_fork_opencensus-1.0.9.dist-info/top_level.txt
opencensus/__init__.py
opencensus/__version__.py
opencensus/common/__init__.py
opencensus/common/http_handler.py
opencensus/common/monitored_resource_util/__init__.py
opencensus/common/monitored_resource_util/aws_identity_doc_utils.py
opencensus/common/monitored_resource_util/gcp_metadata_config.py
opencensus/common/monitored_resource_util/monitored_resource.py
opencensus/common/monitored_resource_util/monitored_resource_util.py
opencensus/common/transports/__init__.py
opencensus/common/transports/async_.py
opencensus/common/transports/base.py
opencensus/common/transports/sync.py
opencensus/metrics/__init__.py
opencensus/metrics/label_key.py
opencensus/metrics/label_value.py
opencensus/metrics/export/__init__.py
opencensus/metrics/export/metric.py
opencensus/metrics/export/metric_descriptor.py
opencensus/metrics/export/point.py
opencensus/metrics/export/summary.py
opencensus/metrics/export/time_series.py
opencensus/metrics/export/value.py
opencensus/stats/__init__.py
opencensus/stats/aggregation.py
opencensus/stats/aggregation_data.py
opencensus/stats/bucket_boundaries.py
opencensus/stats/execution_context.py
opencensus/stats/measure.py
opencensus/stats/measure_to_view_map.py
opencensus/stats/measurement.py
opencensus/stats/measurement_map.py
opencensus/stats/metric_utils.py
opencensus/stats/stats.py
opencensus/stats/stats_recorder.py
opencensus/stats/view.py
opencensus/stats/view_data.py
opencensus/stats/view_manager.py
opencensus/stats/exporters/__init__.py
opencensus/stats/exporters/base.py
opencensus/stats/exporters/prometheus_exporter.py
opencensus/stats/exporters/stackdriver_exporter.py
opencensus/tags/__init__.py
opencensus/tags/execution_context.py
opencensus/tags/tag.py
opencensus/tags/tag_key.py
opencensus/tags/tag_map.py
opencensus/tags/tag_value.py
opencensus/tags/validation.py
opencensus/tags/propagation/__init__.py
opencensus/tags/propagation/binary_serializer.py
opencensus/trace/__init__.py
