Metadata-Version: 2.1
Name: criteo-fork-opencensus
Version: 1.0.9
Summary: A stats collection and distributed tracing framework
Home-page: https://github.com/census-instrumentation/opencensus-python
Author: OpenCensus Authors
Author-email: census-developers@googlegroups.com
License: Apache-2.0
Platform: UNKNOWN
Classifier: Intended Audience :: Developers
Classifier: Development Status :: 3 - Alpha
Classifier: Intended Audience :: Developers
Classifier: License :: OSI Approved :: Apache Software License
Classifier: Programming Language :: Python
Classifier: Programming Language :: Python :: 2
Classifier: Programming Language :: Python :: 2.7
Classifier: Programming Language :: Python :: 3
Classifier: Programming Language :: Python :: 3.4
Classifier: Programming Language :: Python :: 3.5
Classifier: Programming Language :: Python :: 3.6
Provides-Extra: stackdriver
Provides-Extra: prometheus_client
Requires-Dist: google-api-core (<2.0.0,>=0.1.1)
Provides-Extra: prometheus_client
Requires-Dist: prometheus-client (==0.3.1); extra == 'prometheus_client'
Provides-Extra: stackdriver
Requires-Dist: google-cloud-trace (<0.20,>=0.17.0); extra == 'stackdriver'
